oris/__init__.py
oris/models.py
oris/utils.py
oris/parse/oris.g4
oris-0.0.1.dist-info/LICENSE
oris-0.0.1.dist-info/METADATA
oris-0.0.1.dist-info/WHEEL
oris-0.0.1.dist-info/top_level.txt
oris-0.0.1.dist-info/RECORD
